{
    "date": "2026-06-29 15:05",
    "terrestrial": [
        {
            "rank": "1",
            "program": "사랑을처방해드립니다",
            "channel": "KBS2",
            "rate": "15.9"
        },
        {
            "rank": "2",
            "program": "미운우리새끼다시쓰는육아일기",
            "channel": "SBS",
            "rate": "10.7"
        },
        {
            "rank": "3",
            "program": "KBS9시뉴스",
            "channel": "KBS1",
            "rate": "6.8"
        },
        {
            "rank": "4",
            "program": "전국노래자랑",
            "channel": "KBS1",
            "rate": "6.7"
        },
        {
            "rank": "5",
            "program": "1박2일",
            "channel": "KBS2",
            "rate": "6"
        },
        {
            "rank": "6",
            "program": "KBS뉴스(12:00)",
            "channel": "KBS1",
            "rate": "4.6"
        },
        {
            "rank": "7",
            "program": "MBC뉴스데스크",
            "channel": "MBC",
            "rate": "4.3"
        },
        {
            "rank": "8",
            "program": "사장님귀는당나귀귀",
            "channel": "KBS2",
            "rate": "3.2"
        },
        {
            "rank": "8",
            "program": "이슈PICK쌤과함께",
            "channel": "KBS1",
            "rate": "3.2"
        },
        {
            "rank": "10",
            "program": "TV동물농장",
            "channel": "SBS",
            "rate": "3.1"
        },
        {
            "rank": "10",
            "program": "SBS8뉴스",
            "channel": "SBS",
            "rate": "3.1"
        },
        {
            "rank": "10",
            "program": "FIFAWORLDCUP2026(예선콩고민주공화국:우즈베키스탄)",
            "channel": "KBS2",
            "rate": "3.1"
        },
        {
            "rank": "13",
            "program": "KBS뉴스(19:00)",
            "channel": "KBS1",
            "rate": "2.9"
        },
        {
            "rank": "14",
            "program": "탐사기획스트레이트",
            "channel": "MBC",
            "rate": "2.8"
        },
        {
            "rank": "15",
            "program": "김부장<재>",
            "channel": "SBS",
            "rate": "2.7"
        },
        {
            "rank": "15",
            "program": "바다건너사랑",
            "channel": "KBS1",
            "rate": "2.7"
        },
        {
            "rank": "17",
            "program": "런닝맨",
            "channel": "SBS",
            "rate": "2.6"
        },
        {
            "rank": "17",
            "program": "TV쇼진품명품",
            "channel": "KBS1",
            "rate": "2.6"
        },
        {
            "rank": "17",
            "program": "특파원보고세계는지금<재>",
            "channel": "KBS1",
            "rate": "2.6"
        },
        {
            "rank": "20",
            "program": "김부장<재>",
            "channel": "SBS",
            "rate": "2.5"
        }
    ],
    "comprehensive": [
        {
            "rank": "1",
            "program": "신입사원강회장",
            "channel": "JTBC",
            "rate": "11.06"
        },
        {
            "rank": "2",
            "program": "냉장고를부탁해SINCE2014",
            "channel": "JTBC",
            "rate": "2.62"
        },
        {
            "rank": "3",
            "program": "2026FIFA북중미월드컵",
            "channel": "JTBC",
            "rate": "2.36"
        },
        {
            "rank": "4",
            "program": "이제만나러갑니다",
            "channel": "채널A",
            "rate": "2.04"
        },
        {
            "rank": "5",
            "program": "TV조선뉴스7",
            "channel": "TV CHOSUN",
            "rate": "1.77"
        },
        {
            "rank": "6",
            "program": "뉴스A",
            "channel": "채널A",
            "rate": "1.71"
        },
        {
            "rank": "7",
            "program": "JTBC뉴스룸",
            "channel": "JTBC",
            "rate": "1.71"
        },
        {
            "rank": "8",
            "program": "휴먼다큐(사노라면)",
            "channel": "MBN",
            "rate": "1.69"
        },
        {
            "rank": "9",
            "program": "미스트롯포유<재>",
            "channel": "TV CHOSUN",
            "rate": "1.6"
        },
        {
            "rank": "10",
            "program": "신입사원강회장<재>",
            "channel": "JTBC",
            "rate": "1.5"
        },
        {
            "rank": "11",
            "program": "시사팩트플러스",
            "channel": "TV CHOSUN",
            "rate": "1.4"
        },
        {
            "rank": "12",
            "program": "신입사원강회장<재>",
            "channel": "JTBC",
            "rate": "1.36"
        },
        {
            "rank": "13",
            "program": "2026FIFA북중미월드컵",
            "channel": "JTBC",
            "rate": "1.3"
        },
        {
            "rank": "14",
            "program": "MBN뉴스센터",
            "channel": "MBN",
            "rate": "1.28"
        },
        {
            "rank": "15",
            "program": "시사스페셜",
            "channel": "MBN",
            "rate": "1.25"
        },
        {
            "rank": "16",
            "program": "TV조선뉴스현장",
            "channel": "TV CHOSUN",
            "rate": "1.23"
        },
        {
            "rank": "16",
            "program": "무명전설콘서트<재>",
            "channel": "MBN",
            "rate": "1.23"
        },
        {
            "rank": "18",
            "program": "뉴스TOP10",
            "channel": "채널A",
            "rate": "1.22"
        },
        {
            "rank": "19",
            "program": "2026FIFA북중미월드컵",
            "channel": "JTBC",
            "rate": "1.08"
        },
        {
            "rank": "20",
            "program": "특종세상<재>",
            "channel": "MBN",
            "rate": "1.07"
        }
    ],
    "cable": [
        {
            "rank": "1",
            "program": "파친코",
            "channel": "tvN",
            "rate": "2.87"
        },
        {
            "rank": "2",
            "program": "스트릿레스토랑파이터",
            "channel": "tvN",
            "rate": "1.97"
        },
        {
            "rank": "3",
            "program": "2026KBO리그",
            "channel": "KBSN스포츠",
            "rate": "1.94"
        },
        {
            "rank": "4",
            "program": "2026KBO리그",
            "channel": "SBS Sports",
            "rate": "1.88"
        },
        {
            "rank": "5",
            "program": "2026KBO리그",
            "channel": "SPOTV",
            "rate": "1.69"
        },
        {
            "rank": "6",
            "program": "김부장<재>",
            "channel": "SBS Plus",
            "rate": "1.6"
        },
        {
            "rank": "7",
            "program": "뉴스와이드(07:50)",
            "channel": "YTN",
            "rate": "1.6"
        },
        {
            "rank": "8",
            "program": "뉴스START3부",
            "channel": "YTN",
            "rate": "1.59"
        },
        {
            "rank": "9",
            "program": "뉴스와이드(15:50)",
            "channel": "YTN",
            "rate": "1.52"
        },
        {
            "rank": "10",
            "program": "YTN24(14:50)",
            "channel": "YTN",
            "rate": "1.47"
        },
        {
            "rank": "11",
            "program": "뉴스와이드(09:50)",
            "channel": "YTN",
            "rate": "1.32"
        },
        {
            "rank": "12",
            "program": "뉴스와이드(21:50)",
            "channel": "YTN",
            "rate": "1.32"
        },
        {
            "rank": "13",
            "program": "와이드08",
            "channel": "연합뉴스TV",
            "rate": "1.31"
        },
        {
            "rank": "14",
            "program": "뉴스START2부",
            "channel": "YTN",
            "rate": "1.27"
        },
        {
            "rank": "15",
            "program": "명품리포트맥",
            "channel": "연합뉴스TV",
            "rate": "1.26"
        },
        {
            "rank": "16",
            "program": "뉴스와이드(11:50)",
            "channel": "YTN",
            "rate": "1.24"
        },
        {
            "rank": "17",
            "program": "와이드17",
            "channel": "연합뉴스TV",
            "rate": "1.24"
        },
        {
            "rank": "18",
            "program": "김부장",
            "channel": "ENA",
            "rate": "1.23"
        },
        {
            "rank": "19",
            "program": "뉴스오늘3부",
            "channel": "연합뉴스TV",
            "rate": "1.22"
        },
        {
            "rank": "20",
            "program": "2026KBO리그",
            "channel": "SPOTV2",
            "rate": "1.21"
        }
    ]
}